setup.py
tests/test_facemesh.py
tests/test_mnn.py
tests/test_openvino.py
tests/test_yolov5rt.py
wanwu/__init__.py
wanwu/version.py
wanwu/wanwu.py
wanwu.egg-info/PKG-INFO
wanwu.egg-info/SOURCES.txt
wanwu.egg-info/dependency_links.txt
wanwu.egg-info/entry_points.txt
wanwu.egg-info/requires.txt
wanwu.egg-info/top_level.txt
wanwu/base/base_task.py
wanwu/cls/cls.py
wanwu/core/cellar.py
wanwu/core/dispatcher.py
wanwu/core/enums.py
wanwu/core/graphsurgeon.py
wanwu/core/infer.py
wanwu/core/modelloader.py
wanwu/core/backends/base.py
wanwu/core/backends/mnn.py
wanwu/core/backends/ncnn.py
wanwu/core/backends/openvino.py
wanwu/core/backends/ort.py
wanwu/core/backends/ppl.py
wanwu/core/backends/trt.py
wanwu/core/backends/wnn.py
wanwu/det/det.py
wanwu/det/face.py
wanwu/kps/kps.py
wanwu/kps/utils.py
wanwu/seg/seg.py
wanwu/track/__init__.py
wanwu/track/deepsort.py
wanwu/track/kalman_filter.py
wanwu/track/linear_assignment.py
wanwu/track/matching.py
wanwu/track/reid.py
wanwu/track/tracker.py
wanwu/utils/boxes_utils.py
wanwu/utils/gpu_utils.py
wanwu/utils/image_utils.py