Metadata-Version: 2.1
Name: wanwu
Version: 0.1.3
Summary: Wanwu: Everything can have intelligence
Home-page: https://github.com/jinfagang/wanwu
Author: Lucas Jin
Author-email: jinfagang19@163.com
License: GPL-3.0
Keywords: deep learning,script helper,tools
Platform: any
Requires-Dist: colorama
Requires-Dist: requests
Requires-Dist: numpy
Requires-Dist: future
Requires-Dist: onnx
Requires-Dist: deprecated
Requires-Dist: alfred-py
Requires-Dist: onnxruntime
Requires-Dist: tabulate
